CHANGELOG.rst
CONTRIBUTORS.rst
MANIFEST.in
README.rst
setup.cfg
setup.py
tmc/__init__.py
tmc/__main__.py
tmc/api.py
tmc/coloring.py
tmc/config.py
tmc/errors.py
tmc/files.py
tmc/models.py
tmc/unicode_characters.py
tmc/version.py
tmc.egg-info/PKG-INFO
tmc.egg-info/SOURCES.txt
tmc.egg-info/dependency_links.txt
tmc.egg-info/entry_points.txt
tmc.egg-info/requires.txt
tmc.egg-info/top_level.txt
tmc/exercise_tests/__init__.py
tmc/exercise_tests/basetest.py
tmc/exercise_tests/check.py
tmc/exercise_tests/gtest.py
tmc/exercise_tests/java.py
tmc/tests/__init__.py
tmc/ui/__init__.py
tmc/ui/menu.py
tmc/ui/prompt.py
tmc/ui/spinner.py