Metadata-Version: 1.1
Name: tmc
Version: 0.3.17
Summary: TestMyCode client
Home-page: http://github.com/JuhaniImberg/tmc.py/
Author: Juhani Imberg
Author-email: juhani@imberg.com
License: MIT
Platform: UNKNOWN
Classifier: Development Status :: 3 - Alpha
Classifier: Environment :: Console
Classifier: Environment :: Console :: Curses
Classifier: Intended Audience :: Developers
Classifier: License :: OSI Approved :: MIT License
Classifier: Programming Language :: Python :: 3
Classifier: Programming Language :: Python :: 3.2
Classifier: Programming Language :: Python :: 3.3
Classifier: Programming Language :: Python :: 3.4
